fhi_aims_step/__init__.py
fhi_aims_step/_version.py
fhi_aims_step/energy.py
fhi_aims_step/energy_parameters.py
fhi_aims_step/energy_step.py
fhi_aims_step/fhi_aims.py
fhi_aims_step/fhi_aims_parameters.py
fhi_aims_step/fhi_aims_step.py
fhi_aims_step/metadata.py
fhi_aims_step/optimization.py
fhi_aims_step/optimization_parameters.py
fhi_aims_step/optimization_step.py
fhi_aims_step/substep.py
fhi_aims_step/tk_energy.py
fhi_aims_step/tk_fhi_aims.py
fhi_aims_step/tk_optimization.py
fhi_aims_step/data/configuration.txt
fhi_aims_step/data/fhi-aims.ini
fhi_aims_step/data/properties.csv
fhi_aims_step/data/references.bib
fhi_aims_step-2024.10.31.dist-info/AUTHORS.rst
fhi_aims_step-2024.10.31.dist-info/LICENSE
fhi_aims_step-2024.10.31.dist-info/METADATA
fhi_aims_step-2024.10.31.dist-info/WHEEL
fhi_aims_step-2024.10.31.dist-info/entry_points.txt
fhi_aims_step-2024.10.31.dist-info/top_level.txt
fhi_aims_step-2024.10.31.dist-info/zip-safe
fhi_aims_step-2024.10.31.dist-info/RECORD
